shar_sho/__init__.py
shar_sho/cleaning.py
shar_sho/testing.py
shar_sho-0.1.dist-info/LICENSE.txt
shar_sho-0.1.dist-info/METADATA
shar_sho-0.1.dist-info/WHEEL
shar_sho-0.1.dist-info/top_level.txt
shar_sho-0.1.dist-info/RECORD
