Metadata-Version: 2.1
Name: shar-sho
Version: 0.1
Summary: This package is used to clean NLP texts
Home-page: UNKNOWN
Author: shourya
Author-email: shouryareddy306@gmail.com
License: UNKNOWN
Platform: UNKNOWN
Classifier: Programming Language :: Python :: 3
Classifier: License :: OSI Approved :: MIT License
Classifier: Operating System :: OS Independent
License-File: LICENSE.txt
